weo/__init__.py
weo/dataframe.py
weo/dates.py
weo-0.8.4.dist-info/METADATA
weo-0.8.4.dist-info/WHEEL
weo-0.8.4.dist-info/RECORD
