Metadata-Version: 2.1
Name: weo
Version: 0.8.4
Summary: Python client to download IMF World Economic Outlook (WEO) dataset as pandas dataframes.
Home-page: https://github.com/epogrebnyak/weo-reader
Author: Evgeny Pogrebnyak
Author-email: e.pogrebnyak@gmail.com
Requires-Python: >=3.9,<4.0
Classifier: Programming Language :: Python :: 3
Classifier: Programming Language :: Python :: 3.9
Classifier: Programming Language :: Python :: 3.10
Classifier: Programming Language :: Python :: 3.11
Classifier: Programming Language :: Python :: 3.12
Requires-Dist: httpx (>=0.27,<0.28)
Requires-Dist: iso3166 (>=2.1.1,<3.0.0)
Requires-Dist: pandas (>=2.1.0,<3.0.0)
